vcf2seq/__init__.py
vcf2seq/ascii.py
vcf2seq/info.py
vcf2seq/vcf2seq.py
vcf2seq-0.9.2.dist-info/licenses/LICENCE.md
vcf2seq-0.9.2.dist-info/METADATA
vcf2seq-0.9.2.dist-info/WHEEL
vcf2seq-0.9.2.dist-info/entry_points.txt
vcf2seq-0.9.2.dist-info/top_level.txt
vcf2seq-0.9.2.dist-info/RECORD
