Metadata-Version: 2.4
Name: vcf2seq
Version: 0.9.2
Summary: Inputing a VCF file, it returns the genomic sequence at the specified length (31 by default).
Home-page: https://github.com/bio2m/vcf2seq
Author: Benoit Guibert
Author-email: benoit.guibert@free.fr
License: GPLv3
Classifier: Development Status :: 3 - Alpha
Classifier: License :: OSI Approved :: GNU General Public License v3 (GPLv3)
Classifier: Operating System :: POSIX :: Linux
Classifier: Natural Language :: English
Classifier: Intended Audience :: Science/Research
Requires-Python: >=3.7
License-File: LICENCE.md
Requires-Dist: pyfaidx
Dynamic: author
Dynamic: author-email
Dynamic: classifier
Dynamic: description
Dynamic: description-content-type
Dynamic: home-page
Dynamic: license
Dynamic: license-file
Dynamic: requires-dist
Dynamic: requires-python
Dynamic: summary
